<annotation>
	<folder>JPEGImages</folder>
	<filename>2020-04-04 17.59.26.jpg</filename>
	<path>/Users/jennygonzalez/Documents/models/research/object_detection/OwnDataset/dataset/JPEGImages/2020-04-04 17.59.26.jpg</path>
	<source>
		<database>Unknown</database>
	</source>
	<size>
		<width>400</width>
		<height>300</height>
		<depth>3</depth>
	</size>
	<segmented>0</segmented>
	<object>
		<name>breakfast</name>
		<pose>Unspecified</pose>
		<truncated>0</truncated>
		<difficult>0</difficult>
		<bndbox>
			<xmin>149</xmin>
			<ymin>23</ymin>
			<xmax>261</xmax>
			<ymax>288</ymax>
		</bndbox>
	</object>
</annotation>
